Metadata-Version: 2.4
Name: mseep-mcp-server-ccxt
Version: 0.1.4
Summary: Add your description here
Author-email: mseep <support@skydeck.ai>
License-File: LICENSE
Requires-Python: >=3.10
Requires-Dist: ccxt
Requires-Dist: mcp
